vitaleey_cli/__init__.py
vitaleey_cli/__main__.py
vitaleey_cli/cli.py
vitaleey_cli/commands/__init__.py
vitaleey_cli/commands/cluster.py
vitaleey_cli/commands/docker.py
vitaleey_cli/commands/gateway.py
vitaleey_cli/commands/python.py
vitaleey_cli/config/__init__.py
vitaleey_cli/config/application.py
vitaleey_cli/config/config.py
vitaleey_cli/config/git.py
vitaleey_cli/config/kubernetes.py
vitaleey_cli/config/poetry.py
vitaleey_cli/contrib/__init__.py
vitaleey_cli/contrib/api/__init__.py
vitaleey_cli/contrib/api/gateway.py
vitaleey_cli/contrib/api/plugins/__init__.py
vitaleey_cli/contrib/api/plugins/plugin.py
vitaleey_cli/contrib/api/plugins/proxy.py
vitaleey_cli/contrib/api/plugins/router.py
vitaleey_cli/contrib/api/service.py
vitaleey_cli/contrib/api/settings.py
vitaleey_cli/contrib/api/templates/gateway.j2
vitaleey_cli/contrib/api/utils.py
vitaleey_cli/env.py
vitaleey_cli/utils/digitalocean.py
vitaleey_cli/utils/docker.py
vitaleey_cli/utils/git.py
vitaleey_cli/utils/helm.py
vitaleey_cli/utils/krakend.py
vitaleey_cli/utils/kubernetes.py
vitaleey_cli/utils/poetry.py
vitaleey_cli-1.2.2.dist-info/METADATA
vitaleey_cli-1.2.2.dist-info/WHEEL
vitaleey_cli-1.2.2.dist-info/entry_points.txt
vitaleey_cli-1.2.2.dist-info/RECORD
