Metadata-Version: 2.1
Name: vitaleey-cli
Version: 1.2.2
Summary: Vitaleey CLI
Author: Vitaleey
Requires-Python: >=3.12,<4.0
Classifier: Programming Language :: Python :: 3
Classifier: Programming Language :: Python :: 3.12
Requires-Dist: click (>=8.1.7,<9.0.0)
Requires-Dist: cryptography (>=43.0.0,<44.0.0)
Requires-Dist: jinja2 (>=3.1.4,<4.0.0)
Requires-Dist: python-dateutil (>=2.9.0.post0,<3.0.0)
Requires-Dist: python-gitlab (>=5.1.0,<6.0.0)
Requires-Dist: pyyaml (>=6.0.1,<7.0.0)
Requires-Dist: tomli (>=2.0.1,<3.0.0)
